karrio/mappers/chronopost/__init__.py
karrio/mappers/chronopost/mapper.py
karrio/mappers/chronopost/proxy.py
karrio/mappers/chronopost/settings.py
karrio/plugins/chronopost/__init__.py
karrio/providers/chronopost/__init__.py
karrio/providers/chronopost/error.py
karrio/providers/chronopost/rate.py
karrio/providers/chronopost/tracking.py
karrio/providers/chronopost/units.py
karrio/providers/chronopost/utils.py
karrio/providers/chronopost/shipment/__init__.py
karrio/providers/chronopost/shipment/cancel.py
karrio/providers/chronopost/shipment/create.py
karrio/schemas/chronopost/__init__.py
karrio/schemas/chronopost/quickcostservice.py
karrio/schemas/chronopost/shippingservice.py
karrio/schemas/chronopost/trackingservice.py
karrio_chronopost-2026.1.4.dist-info/METADATA
karrio_chronopost-2026.1.4.dist-info/WHEEL
karrio_chronopost-2026.1.4.dist-info/entry_points.txt
karrio_chronopost-2026.1.4.dist-info/top_level.txt
karrio_chronopost-2026.1.4.dist-info/RECORD
